jsonpatch-stubs/__init__.py
jsonpatch-stubs/__init__.pyi
jsonpatch-stubs/py.typed
types_jsonpatch-0.1.0a1.dist-info/LICENSE
types_jsonpatch-0.1.0a1.dist-info/WHEEL
types_jsonpatch-0.1.0a1.dist-info/METADATA
types_jsonpatch-0.1.0a1.dist-info/RECORD
